vokro_dl/__init__.py
vokro_dl/sync.py
vokro_dl/cli/__init__.py
vokro_dl/cli/__main__.py
vokro_dl/cli/main.py
vokro_dl/core/__init__.py
vokro_dl/core/config.py
vokro_dl/core/downloader.py
vokro_dl/core/exceptions.py
vokro_dl/core/models.py
vokro_dl/extractors/__init__.py
vokro_dl/extractors/base.py
vokro_dl/extractors/generic.py
vokro_dl/extractors/registry.py
vokro_dl/extractors/vimeo.py
vokro_dl/extractors/youtube.py
vokro_dl/utils/__init__.py
vokro_dl/utils/metadata.py
vokro_dl/utils/networking.py
vokro_dl/utils/performance.py
vokro_dl/utils/post_processing.py
vokro_dl/utils/progress.py
vokro_dl/utils/quality_selector.py
vokro_dl/utils/retry.py
vokro_dl/utils/subtitles.py
vokro_dl-0.1.0.dist-info/METADATA
vokro_dl-0.1.0.dist-info/WHEEL
vokro_dl-0.1.0.dist-info/entry_points.txt
vokro_dl-0.1.0.dist-info/licenses/LICENSE
vokro_dl-0.1.0.dist-info/RECORD
